self_registration/__init__.py
self_registration/admin.py
self_registration/apps.py
self_registration/gql_mutations.py
self_registration/gql_queries.py
self_registration/models.py
self_registration/schema.py
self_registration/test.py
self_registration/tests.py
self_registration/urls.py
self_registration/views.py
self_registration/migrations/0001_initial.py
self_registration/migrations/0002_auto_20210526_1618.py
self_registration/migrations/0003_notice.py
self_registration/migrations/0004_otp.py
self_registration/migrations/0005_auto_20210530_2156.py
self_registration/migrations/0006_healthfacilitycoordinate.py
self_registration/migrations/0007_voucherpayment.py
self_registration/migrations/0008_voucherpayment_vocher_id.py
self_registration/migrations/0009_auto_20210617_2217.py
self_registration/migrations/0010_auto_20210623_0809.py
self_registration/migrations/0011_auto_20210623_0809.py
self_registration/migrations/0012_auto_20210623_2016.py
self_registration/migrations/0013_auto_20210623_2131.py
self_registration/migrations/0014_auto_20210627_0808.py
self_registration/migrations/0015_auto_20210704_2249.py
self_registration/migrations/0016_auto_20210707_2310.py
self_registration/migrations/0017_auto_20210710_1255.py
self_registration/migrations/0018_auto_20210712_1431.py
self_registration/migrations/0019_auto_20210715_0721.py
self_registration/migrations/0020_auto_20210715_0732.py
self_registration/migrations/0021_alter_voucherpayment_vocher_id.py
self_registration/migrations/__init__.py
openimis_be_self_registration-1.0.1.dist-info/LICENSE.md
openimis_be_self_registration-1.0.1.dist-info/METADATA
openimis_be_self_registration-1.0.1.dist-info/WHEEL
openimis_be_self_registration-1.0.1.dist-info/top_level.txt
openimis_be_self_registration-1.0.1.dist-info/RECORD
