Metadata-Version: 2.1
Name: openimis-be-self-registration
Version: 1.0.1
Summary: The openIMIS self registration reference module.
Home-page: https://openimis.org/
Author: Tinker Technology
Author-email: info@tinker.com.np
License: GNU AGPL v3
Classifier: Environment :: Web Environment
Classifier: Framework :: Django
Classifier: Framework :: Django :: 3.0
Classifier: Intended Audience :: Developers
Classifier: License :: OSI Approved :: GNU Affero General Public License v3
Classifier: Operating System :: OS Independent
Classifier: Programming Language :: Python
Classifier: Programming Language :: Python :: 3.6
Classifier: Programming Language :: Python :: 3.7
License-File: LICENSE.md
Requires-Dist: django
Requires-Dist: django-db-signals
Requires-Dist: djangorestframework
Requires-Dist: openimis-be-core
Requires-Dist: openimis-be-claim-batch
Requires-Dist: openimis-be-insuree
Requires-Dist: openimis-be-location
Requires-Dist: openimis-be-medical
Requires-Dist: openimis-be-policy
Requires-Dist: openimis-be-product
Requires-Dist: openimis-be-report
